Metadata-Version: 2.1
Name: mmpretrain
Version: 1.2.0
Summary: OpenMMLab Model Pretraining Toolbox and Benchmark
Home-page: https://github.com/open-mmlab/mmpretrain
Author: MMPretrain Contributors
Author-email: openmmlab@gmail.com
License: Apache License 2.0
Keywords: computer vision,image classification,unsupervised learning,self-supervised learning
Platform: UNKNOWN
Classifier: Development Status :: 4 - Beta
Classifier: License :: OSI Approved :: Apache Software License
Classifier: Operating System :: OS Independent
Classifier: Programming Language :: Python :: 3
Classifier: Programming Language :: Python :: 3.7
Classifier: Programming Language :: Python :: 3.8
Classifier: Programming Language :: Python :: 3.9
Classifier: Programming Language :: Python :: 3.10
Classifier: Programming Language :: Python :: 3.11
Classifier: Topic :: Scientific/Engineering :: Artificial Intelligence
Requires-Python: >=3.7
Requires-Dist: einops
Requires-Dist: importlib-metadata
Requires-Dist: mat4py
Requires-Dist: matplotlib
Requires-Dist: modelindex
Requires-Dist: numpy
Requires-Dist: rich
Provides-Extra: all
Requires-Dist: albumentations >=0.3.2 ; extra == 'all'
Requires-Dist: grad-cam <1.5.0,>=1.3.7 ; extra == 'all'
Requires-Dist: requests ; extra == 'all'
Requires-Dist: scikit-learn ; extra == 'all'
Requires-Dist: einops ; extra == 'all'
Requires-Dist: importlib-metadata ; extra == 'all'
Requires-Dist: mat4py ; extra == 'all'
Requires-Dist: matplotlib ; extra == 'all'
Requires-Dist: modelindex ; extra == 'all'
Requires-Dist: numpy ; extra == 'all'
Requires-Dist: rich ; extra == 'all'
Requires-Dist: coverage ; extra == 'all'
Requires-Dist: interrogate ; extra == 'all'
Requires-Dist: pytest ; extra == 'all'
Provides-Extra: mim
Requires-Dist: mmcv <2.4.0,>=2.0.0 ; extra == 'mim'
Requires-Dist: mmengine <1.0.0,>=0.8.3 ; extra == 'mim'
Provides-Extra: multimodal
Requires-Dist: pycocotools ; extra == 'multimodal'
Requires-Dist: transformers >=4.28.0 ; extra == 'multimodal'
Provides-Extra: optional
Requires-Dist: albumentations >=0.3.2 ; extra == 'optional'
Requires-Dist: grad-cam <1.5.0,>=1.3.7 ; extra == 'optional'
Requires-Dist: requests ; extra == 'optional'
Requires-Dist: scikit-learn ; extra == 'optional'
Provides-Extra: tests
Requires-Dist: coverage ; extra == 'tests'
Requires-Dist: interrogate ; extra == 'tests'
Requires-Dist: pytest ; extra == 'tests'
